Metadata-Version: 2.1
Name: django-mercadopago
Version: 6.0.1
Summary: MercadoPago integration for django
Home-page: https://github.com/WhyNotHugo/django-mercadopago
Author: Hugo Osvaldo Barrera
Author-email: hugo@barrera.io
License: ISC
Platform: UNKNOWN
Classifier: Development Status :: 5 - Production/Stable
Classifier: Environment :: Web Environment
Classifier: Framework :: Django :: 2.2
Classifier: Framework :: Django :: 3.0
Classifier: Framework :: Django :: 3.1
Classifier: Framework :: Django
Classifier: Intended Audience :: Developers
Classifier: Programming Language :: Python :: 3
Classifier: Programming Language :: Python :: 3.5
Classifier: Programming Language :: Python :: 3.6
Classifier: Programming Language :: Python :: 3.7
Classifier: Programming Language :: Python :: 3.8
Classifier: Programming Language :: Python :: 3 :: Only
Classifier: Topic :: Internet :: WWW/HTTP
Classifier: Topic :: Software Development :: Libraries :: Python Modules
Requires-Dist: wheel (>=0.26.0)
Requires-Dist: Django (>=2.2.0)
Requires-Dist: mercadopago (<1.0.0)
Requires-Dist: setuptools-git (>=1.1)
Requires-Dist: setuptools-scm (>=1.8.0)
Provides-Extra: fixtures
Requires-Dist: factory-boy ; extra == 'fixtures'
